musdl.py
musdl-3.1.8.dist-info/entry_points.txt
musdl-3.1.8.dist-info/LICENSE
musdl-3.1.8.dist-info/WHEEL
musdl-3.1.8.dist-info/METADATA
musdl-3.1.8.dist-info/RECORD
