Metadata-Version: 2.1
Name: musdl
Version: 3.1.8
Summary: [mus]escore [d]own[l]oader, ported from TypeScript
Home-page: https://github.com/ongyx/musdl
Author: Ong Yong Xin
Author-email: ongyongxin2020+github@gmail.com
Requires-Python: >=3.6
Classifier: Programming Language :: Python :: 3
Classifier: License :: OSI Approved :: MIT License
Classifier: Operating System :: OS Independent
Requires-Dist: beautifulsoup4>=4.9.2
Requires-Dist: requests>=2.24.0
Requires-Dist: dataclasses; python_version == '3.6'
Requires-Dist: pydoc-markdown>=3.10.1 ; extra == "doc"
Provides-Extra: doc
